flaat/__init__.py
flaat/access_tokens.py
flaat/caches.py
flaat/config.py
flaat/exceptions.py
flaat/flaat_userinfo.py
flaat/issuers.py
flaat/requirements.py
flaat/test_env.py
flaat/user_infos.py
flaat/aio/__init__.py
flaat/aio/aio_test.py
flaat/aio/overrides_test.py
flaat/fastapi/__init__.py
flaat/fastapi/fastapi_test.py
flaat/flask/__init__.py
flaat/flask/conftest.py
flaat/flask/flask_test.py
flaat/flask/flask_test_cases.py
flaat/tests/access_tokens_test.py
flaat/tests/flaat_test.py
flaat/tests/flaat_userinfo_test.py
flaat/tests/issuers_test.py
flaat/tests/requirements_test.py
flaat-1.1.18.dist-info/LICENSE
flaat-1.1.18.dist-info/METADATA
flaat-1.1.18.dist-info/WHEEL
flaat-1.1.18.dist-info/entry_points.txt
flaat-1.1.18.dist-info/pbr.json
flaat-1.1.18.dist-info/top_level.txt
flaat-1.1.18.dist-info/RECORD
