Metadata-Version: 2.1
Name: flaat
Version: 1.1.18
Summary: User authorization for OIDC authenticated python web APIs.
Home-page: https://github.com/indigo-dc/flaat
Author: Marcus Hardt
Author-email: hardt@kit.edu
License: MIT
Project-URL: Bug Tracker, https://github.com/indigo-dc/flaat/issues
Project-URL: Documentation, https://flaat.readthedocs.io/en/latest/
Classifier: Environment :: Console
Classifier: Environment :: Web Environment
Classifier: Framework :: Flask
Classifier: Intended Audience :: Developers
Classifier: Intended Audience :: Information Technology
Classifier: Intended Audience :: Science/Research
Classifier: Intended Audience :: System Administrators
Classifier: License :: OSI Approved :: MIT License
Classifier: Operating System :: OS Independent
Classifier: Natural Language :: English
Classifier: Programming Language :: Python :: 3
Classifier: Topic :: Internet :: WWW/HTTP
Classifier: Topic :: System :: Systems Administration
Classifier: Topic :: System :: Systems Administration :: Authentication/Directory
License-File: LICENSE
Requires-Dist: aarc-entitlement ==1.*
Requires-Dist: cachetools ==5.*
Requires-Dist: configargparse ==1.*
Requires-Dist: humanfriendly ==10.*
Requires-Dist: liboidcagent ==0.*
Requires-Dist: requests >=2.31
Requires-Dist: pyjwt[crypto] >=2.4
Requires-Dist: cryptography >=37
Provides-Extra: aiohttp
Requires-Dist: aiohttp ; extra == 'aiohttp'
Provides-Extra: fastapi
Requires-Dist: fastapi >=0.61.2 ; extra == 'fastapi'
Provides-Extra: flask
Requires-Dist: Flask ; extra == 'flask'
Provides-Extra: test
Requires-Dist: python-dotenv ; extra == 'test'
Requires-Dist: pytest <8 ; extra == 'test'
Requires-Dist: pytest-aiohttp ; extra == 'test'
Requires-Dist: pytest-cov ; extra == 'test'
Requires-Dist: pytest-cases ; extra == 'test'
Requires-Dist: pylint-pytest ; extra == 'test'
Requires-Dist: aiohttp ; extra == 'test'
Requires-Dist: fastapi[all] >=0.61.2 ; extra == 'test'
Requires-Dist: flask ; extra == 'test'
Requires-Dist: types-Flask ; extra == 'test'
